{
  dataset_id: "dgen_DECARB_2023",
  dataset_type: "modeled",
  data_source: "dgen",
  sector_description: "residential and non-residential",
  description: "dGen Standard Scenarios 2023 with profiles using 2018 as the weather year",
  origin_creator: "Ashreeta Prasanna",
  origin_organization: "NREL",
  origin_contributors: [
    "Ashreeta Prasanna",
    "Paritosh Das",
    "Jane Lockshin",
    "Michaela Sizemore"
  ],
  origin_project: "Standard Scenarios 2023",
  origin_date: "2023-11-01",
  origin_version: "0.1.0",
  source: "dGen runs for Standard Scenrios 2023",
  data_classification: "low",
  tags: [
    "distributed PV",
    "2023",
    "StScen Low RE Cost",
    "High and Breakthrough",
    "DECARB",
  ],
  data_schema_type: "standard",
  trivial_dimensions: [
    "weather_year",
    "scenario",
    "subsector"
  ],
  data_schema: {
    load_data_column_dimension: "metric",
  },
  dimensions: [
    { 
     "class": "County",
      type: "geography",
      name: 'US Census tracts',
      display_name: "Tract",
      file: "dimensions/dgen_tract.csv",
      module: "dsgrid.dimension.standard",
      description: "US tracts for L48, Census 2010 vintage mapped to 2020 counties, no territories",
    },
    {
      type: "sector",
      name: "dGen Sectors",
      display_name: "Res and Non-res",
      file: "dimensions/sectors.csv",
      module: "dsgrid.dimension.standard",
      "class": "Sector",
      description: "dGen models DPV adoption for the residential and non-residential sectors",
    },
      {
        class: 'Subsector',
        description: 'dgen Subsectors',
        file: 'dimensions/subsectors.csv',
        module: 'dsgrid.dimension.standard',
        name: 'CONUS-2022-Detailed-Subsectors',
        display_name: 'Subsector',
        type: 'subsector',
      },
    {
      type: "metric",
      name: "dgen DPV Generation",
      display_name: "DPV generation",
      file: "dimensions/dpv_generation.csv",
      module: "dsgrid.dimension.standard",
      "class": "EnergyEndUse",
      description: "dGen DPV generation in kWh",
    },
    {
      type: "scenario",
      name: "StScen2022_Low_RE_Cost_LMI",
      display_name: "StScen2022_Low_RE_Cost",
      file: "dimensions/scenario.csv",
      module: "dsgrid.dimension.standard",
      "class": "Scenario",
      description: "reeds scenario High and Breakthrough mapped to dGen scenario StScen2022_Low_RE_Cost",
    },
    {
      type: "model_year",
      name: "dGen model years",
      display_name: "dGen Model Years",
      file: "dimensions/model_years.csv",
      module: "dsgrid.dimension.standard",
      "class": "ModelYear",     
      description: "dGen modeling years for Standard Scenarios, 2024-2050",
    },
    {
      "class": "WeatherYear",
      description: "Weather year, 2018 only",
      file: "dimensions/weather_year.csv",
      module: "dsgrid.dimension.standard",
      name: "2018 Weather Year",
      display_name: "Weather 2018",
      type: "weather_year",
    },
    {
      type: 'time',
      class: 'Time',
      frequency: 'P0DT1H0M0.000000S',
      name: 'Time-2018-EST-hourly-periodBeginning-noLeapDayAdjustment-total',
      display_name: 'Time EST',
      time_type: 'datetime',
      leap_day_adjustment: 'none',
      description: 'Time dimension, 2018 hourly EST, hour-beginning, no Leap Day Adjustment, total value',
      time_interval_type: 'period_beginning',
      str_format: '%Y-%m-%d %H:%M:%S',
      timezone: 'UTC',
      measurement_type: 'total',
      ranges: [
            {
                start: '2018-01-01 00:00:00',
                end: '2018-12-31 23:00:00',
            },
        ],
    }, ]
}    
